pokie/__init__.py
pokie/_version.py
pokie/pokie.py
pokie_score-0.1.7.dev0.dist-info/METADATA
pokie_score-0.1.7.dev0.dist-info/WHEEL
pokie_score-0.1.7.dev0.dist-info/licenses/LICENSE
pokie_score-0.1.7.dev0.dist-info/RECORD
