Metadata-Version: 2.4
Name: pokie_score
Version: 0.1.7.dev0
Summary: Implemenation of the Pokie from Sharief et al. 2025
Project-URL: Homepage, https://github.com/SammyS15/Pokie
Project-URL: Documentation, https://github.com/SammyS15/Pokie
Project-URL: Repository, https://github.com/SammyS15/Pokie
Project-URL: Issues, https://github.com/SammyS15/Pokie/issues
Author-email: Sammy Sharief <sammybassoon1516@hotmail.com>, Justine Zeghal <zghjustinephd@gmail.com>
License: MIT License
License-File: LICENSE
Keywords: machine learning,pytorch,statistics
Classifier: Development Status :: 1 - Planning
Classifier: Intended Audience :: Science/Research
Classifier: License :: OSI Approved :: MIT License
Classifier: Operating System :: OS Independent
Classifier: Programming Language :: Python :: 3
Requires-Python: >=3.9
Requires-Dist: numpy
Requires-Dist: scipy
Requires-Dist: torch
Requires-Dist: tqdm
Provides-Extra: dev
Requires-Dist: pytest-cov<5,>=4.1; extra == 'dev'
Requires-Dist: pytest-mock<4,>=3.12; extra == 'dev'
Requires-Dist: pytest<9,>=8.0; extra == 'dev'
